{
    "left": {
        "left": {
            "left": {
                "left": {
                    "left": {
                        "left": {
                            "left": {
                                "left": {
                                    "left": {
                                        "left": {
                                            "result": 0
                                        },
                                        "right": {
                                            "result": 4
                                        },
                                        "operator": "<lambda>"
                                    },
                                    "right": {
                                        "result": 4
                                    },
                                    "operator": "<lambda>"
                                },
                                "right": {
                                    "result": 4
                                },
                                "operator": "<lambda>"
                            },
                            "right": {
                                "result": 4
                            },
                            "operator": "<lambda>"
                        },
                        "right": {
                            "result": 4
                        },
                        "operator": "<lambda>"
                    },
                    "right": {
                        "result": 4
                    },
                    "operator": "<lambda>"
                },
                "right": {
                    "result": 4
                },
                "operator": "<lambda>"
            },
            "right": {
                "result": 4
            },
            "operator": "<lambda>"
        },
        "right": {
            "result": 4
        },
        "operator": "<lambda>"
    },
    "right": {
        "result": 4
    },
    "operator": "<lambda>"
}